{"season":  "2008",
  "teams":  [
    {"name": "Los Angeles Sparks",
      "roster":  ["Shannon Bobbitt",
        "Kiesha Brown",
        "Margo Dydek",
        "Marie Ferdinand-Harris",
        "Kamela Gissendanner",
        "Amber Jacobs",
        "Temeka Johnson",
        "Lisa Leslie",
        "Raffaella Masciadri",
        "DeLisha Milton-Jones",
        "Jessica Moore",
        "Murriel Page",
        "Candace Parker",
        "Sidney Spencer",
        "Christi Thomas"]},
    {"name":  "Houston Comets",
      "roster":  ["Matee Ajavon",
        "Mistie Bass",
        "Latasha Byears",
        "Tamecka Dixon",
        "Roneeka Hodges",
        "Sequoia Holmes",
        "Shannon Johnson",
        "Sancho Lyttle",
        "Mwadi Mabika",
        "Hamchetou Maiga-Ba",
        "Ashley Shields",
        "Michelle Snow",
        "Tina Thompson",
        "Marcedes Walker",
        "Erica White"]},
    {"name":  "Connecticut Sun",
      "roster":  ["Svetlana Abrosimova",
        "Jolene Anderson",
        "Jamie Carey",
        "Kerri Gardin",
        "Sandrine Gruda",
        "Amber Holt",
        "Asjha Jones",
        "Danielle Page",
        "Erin Phillips",
        "Ketia Swanier",
        "Barbara Turner",
        "Lindsay Whalen",
        "Tamika Whitmore",
        "Tamika Williams"]},
    {"name":  "Phoenix Mercury",
      "roster":  ["Willnett Crockett",
        "Jennifer Derevjanik",
        "Barbara Farris",
        "Kelly Mazzante",
        "Kelly Miller",
        "Yuko Oga",
        "Cappie Pondexter",
        "LaToya Sanders",
        "Allie Quigley",
        "Olympia Scott",
        "Brooke Smith",
        "Tangela Smith",
        "Diana Taurasi",
        "Le'coe Willingham"]},
    {"name":  "New York Liberty",
      "roster":  ["Ashley Battle",
        "Essence Carson",
        "Shameka Christon",
        "Jessica Davenport",
        "Megan Duffy",
        "Tiffany Jackson-Jones",
        "Cathrine Kraayeveld",
        "Erlana Larkins",
        "Janel McCarville",
        "Leilani Mitchell",
        "Loree Moore",
        "Erin Thorn",
        "Lisa Willis"]},
    {"name":  "Sacramento Monarchs",
      "roster":  ["Charel Allen",
        "La'Tangela Atkinson",
        "Rebekkah Brunson",
        "Scholanda Dorrell",
        "A'Quonesia Franklin",
        "Laura Harper",
        "Crystal Kelly",
        "Kara Lawson",
        "Chelsea Newton",
        "Ticha Penicheiro",
        "Nicole Powell",
        "Kim Smith",
        "DeMya Walker",
        "Adrian Williams-Strong"]},
    {"name":  "Detroit Shock",
      "roster":  ["Kara Braxton",
        "Cheryl Ford",
        "Chrissy Givens",
        "Alexis Hornbuckle",
        "Tasha Humphrey",
        "Nancy Lieberman",
        "Stacey Lovelace",
        "Taj McWilliams-Franklin",
        "Shay Murphy",
        "Deanna Nolan",
        "Plenette Pierson",
        "Elaine Powell",
        "Sheri Sam",
        "Olayinka Sanni",
        "Kelly Schumacher",
        "Ashley Shields",
        "Katie Smith",
        "Wanisha Smith",
        "LaToya Thomas"]},
    {"name":  "Minnesota Lynx",
      "roster":  ["Nicky Anosike",
        "Seimone Augustus",
        "Anna DeForge",
        "Lindsey Harding",
        "Vanessa Hayden",
        "Charde Houston",
        "Navonda Moore",
        "Shay Murphy",
        "Nicole Ohlde",
        "Noelle Quinn",
        "Kristen Rasmussen",
        "Crystal Smith",
        "LaToya Thomas",
        "Candice Wiggins",
        "Sharnee Zoll"]},
    {"name":  "Detroit Shock",
      "roster":  ["Morenike Atunrase",
        "Val Berezhynska",
        "Helen Darling",
        "Becky Hammon",
        "Sandora Irvin",
        "Vickie Johnson",
        "Edwige Lawson-Wade",
        "Erin Perperoglou",
        "Ruth Riley",
        "Adrianne Ross",
        "Ann Wauters",
        "Brittany Wilkins",
        "Sophia Young-Malcolm"]},
    {"name":  "Washington Mystics",
      "roster":  ["Sherill Baker",
        "Alison Bales",
        "Tully Bevilaqua",
        "LaToya Bond",
        "Tamika Catchings",
        "Katie Douglas",
        "Allison Feaster",
        "Doneeka Lewis",
        "Ebony Hoffman",
        "Kristen Mann",
        "Bernadette Ngoyisa",
        "Tammy Sutton-Brown",
        "Kasha Terry",
        "Tan White",
        "Khadijah Whittington"]},
    {"name":  "Atlanta Dream",
      "roster":  ["Alison Bales",
        "Iziane Castro Marques",
        "Erika de Souza",
        "Kristin Haynie",
        "Jennifer Lacy",
        "Ivory Latta",
        "Betty Lennox",
        "Camille Little",
        "Stacey Lovelace",
        "Kristen Mann",
        "Katie Mattera",
        "Chioma Nnamaka",
        "Ann Strother",
        "Kasha Terry",
        "Tamera Young"]},
    {"name":  "Seattle Storm",
      "roster":  ["Kimberly Beck",
        "Sue Bird",
        "Swin Cash",
        "Shyra Ely-Gash",
        "Katie Gearlds",
        "Yolanda Griffith",
        "Lauren Jackson",
        "Camille Little",
        "Kristen O'Neill",
        "Florina Pascalau",
        "Ashley Robinson",
        "Kelly Santos",
        "Sheryl Swoopes",
        "Tanisha Wright"]},
    {"name":  "Chicago Sky",
      "roster":  ["Dominique Canty",
        "Quianna Chaney",
        "Candice Dupree",
        "Tye'sha Fluker",
        "Sylvia Fowles",
        "Cathy Joens",
        "Chasity Melvin",
        "Jia Perkins",
        "Armintie Herrington",
        "Brooke Queenan",
        "Leah Rush",
        "K.B. Sharp",
        "Brooke Wyckoff"]},
    {"name":  "Indiana Fever",
      "roster":  ["Sherill Baker",
        "Alison Bales",
        "Tully Bevilaqua",
        "LaToya Bond",
        "Tamika Catchings",
        "Katie Douglas",
        "Allison Feaster",
        "Doneeka Lewis",
        "Ebony Hoffman",
        "Kristen Mann",
        "Bernadette Ngoyisa",
        "Tammy Sutton-Brown",
        "Kasha Terry",
        "Tan White",
        "Khadijah Whittington"]}
  ]}